onehot2seq/__init__.py
onehot2seq/main.py
onehot2seq-0.0.2.dist-info/LICENSE
onehot2seq-0.0.2.dist-info/METADATA
onehot2seq-0.0.2.dist-info/WHEEL
onehot2seq-0.0.2.dist-info/entry_points.txt
onehot2seq-0.0.2.dist-info/top_level.txt
onehot2seq-0.0.2.dist-info/RECORD
