Metadata-Version: 2.1
Name: onehot2seq
Version: 0.0.2
Summary: decode a one-hot numpy array to biological sequences
Home-page: https://github.com/akikuno/onehot2seq
Author: Akihiro Kuno
Author-email: akuno@md.tsukuba.ac.jp
License: UNKNOWN
Platform: UNKNOWN
Classifier: Programming Language :: Python :: 3
Classifier: License :: OSI Approved :: MIT License
Classifier: Operating System :: OS Independent
Requires-Python: >=3.7
License-File: LICENSE
Requires-Dist: numpy
